Pyautomators/Ambiente.py
Pyautomators/Dados.py
Pyautomators/Documentacao.py
Pyautomators/Drivers.py
Pyautomators/Error.py
Pyautomators/Inspecionador.py
Pyautomators/Log.py
Pyautomators/Runner_Pyautomators.py
Pyautomators/Runner_in_Container.py
Pyautomators/Verifica.py
Pyautomators/__init__.py
Pyautomators/__main__.py
Pyautomators/banco_de_dados.py
Pyautomators/desk.py
Pyautomators/interoperaveis.py
Pyautomators/mobile.py
Pyautomators/mobile_extesao.py
Pyautomators/models.py
Pyautomators/mouse_teclado.py
Pyautomators/pyautomator.py
Pyautomators/remote.py
Pyautomators/web.py
Pyautomators/web_extensao.py
Pyautomators/BDT/__init__.py
Pyautomators/BDT/__main__.py
Pyautomators/BDT/_stepimport.py
Pyautomators/BDT/_types.py
Pyautomators/BDT/capture.py
Pyautomators/BDT/configuration.py
Pyautomators/BDT/fixture.py
Pyautomators/BDT/i18n.py
Pyautomators/BDT/importer.py
Pyautomators/BDT/json_parser.py
Pyautomators/BDT/log_capture.py
Pyautomators/BDT/matchers.py
Pyautomators/BDT/model.py
Pyautomators/BDT/model_core.py
Pyautomators/BDT/model_describe.py
Pyautomators/BDT/parser.py
Pyautomators/BDT/runner.py
Pyautomators/BDT/runner_util.py
Pyautomators/BDT/step_registry.py
Pyautomators/BDT/tag_expression.py
Pyautomators/BDT/tag_matcher.py
Pyautomators/BDT/textutil.py
Pyautomators/BDT/userdata.py
Pyautomators/BDT/api/__init__.py
Pyautomators/BDT/api/async_step.py
Pyautomators/BDT/compat/__init__.py
Pyautomators/BDT/compat/collections.py
Pyautomators/BDT/contrib/__init__.py
Pyautomators/BDT/contrib/formatter_missing_steps.py
Pyautomators/BDT/contrib/scenario_autoretry.py
Pyautomators/BDT/contrib/substep_dirs.py
Pyautomators/BDT/formatter/__init__.py
Pyautomators/BDT/formatter/_builtins.py
Pyautomators/BDT/formatter/_registry.py
Pyautomators/BDT/formatter/ansi_escapes.py
Pyautomators/BDT/formatter/base.py
Pyautomators/BDT/formatter/cucumber_json.py
Pyautomators/BDT/formatter/cucumber_json_1.2.6.py
Pyautomators-1.6.17.dist-info/METADATA
Pyautomators-1.6.17.dist-info/RECORD
Pyautomators-1.6.17.dist-info/WHEEL
Pyautomators-1.6.17.dist-info/top_level.txt
Pyautomators-1.6.17.dist-info/zip-safe
